{
  "type": "FeatureCollection",
  "features": [
    {
      "type": "Feature",
      "geometry": { "type": "Point", "coordinates": [35.2034, 31.9038] },
      "properties": { "id":"TEST-1", "name":"نقطة اختبار", "status":"مهدد", "era":"الانتداب", "year":1935, "story":"تجربة" }
    }
  ]
}
