{
  "type": "Feature",
  "geometry": { "type": "Point", "coordinates": [35.2034, 31.9038] },
  "properties": {
    "id": "RAM-002",
    "name": "مبنى تاريخي",
    "year": 1935,
    "era": "الانتداب",
    "status": "مهدد",
    "style": "حجري تقليدي",
    "story": "قصة قصيرة ممتعة للسائح…",
    "image": "./images/demo-1.jpg",
    "gallery": ["./images/demo-1.jpg", "./images/demo-2.jpg"],
    "beforeAfter": { "before": "./images/demo-old.jpg", "after": "./images/demo-new.jpg" },
    "audio": "./audio/demo.mp3",
    "link": "https://example.com"
  }
}
